wisent_plots/__init__.py
wisent_plots/assets/pattern_check_mesh.svg
wisent_plots/assets/pattern_crossing_lines.svg
wisent_plots/assets/pattern_diagonal_lines.svg
wisent_plots/assets/pattern_vertical_lines.svg
wisent_plots/assets/large/dither_cross_large.svg
wisent_plots/assets/large/noise_rectangle_large.svg
wisent_plots/charts/__init__.py
wisent_plots/charts/area/area_chart.py
wisent_plots/charts/area/area_chart_components.py
wisent_plots/charts/area/area_chart_renderer.py
wisent_plots/charts/area/svg_area_chart.py
wisent_plots/charts/area/svg_area_chart_2patterns.py
wisent_plots/charts/area/svg_area_chart_gradient.py
wisent_plots/charts/area/svg_area_chart_pattern.py
wisent_plots/charts/bar/bar_chart.py
wisent_plots/charts/bar/svg_bar_chart.py
wisent_plots/charts/bubble/bubble_chart.py
wisent_plots/charts/bubble/svg_bubble_chart.py
wisent_plots/charts/bubble/svg_radar_bubble_chart.py
wisent_plots/charts/column/column_chart.py
wisent_plots/charts/column/svg_column_chart.py
wisent_plots/charts/line/line_chart.py
wisent_plots/charts/line/svg_line_chart.py
wisent_plots/charts/pie/pie_chart.py
wisent_plots/charts/pie/svg_pie_chart.py
wisent_plots/charts/radar/radar_chart.py
wisent_plots/charts/radar/svg_radar_chart.py
wisent_plots/styles/__init__.py
wisent_plots/styles/style_config.py
wisent_visuals-0.1.0.dist-info/licenses/LICENSE
wisent_visuals-0.1.0.dist-info/METADATA
wisent_visuals-0.1.0.dist-info/WHEEL
wisent_visuals-0.1.0.dist-info/top_level.txt
wisent_visuals-0.1.0.dist-info/RECORD
