Metadata-Version: 2.4
Name: wisent-visuals
Version: 0.1.0
Summary: Create beautiful plots in Wisent brand styling
Author-email: Wisent <info@wisent.com>
License: MIT
Project-URL: Homepage, https://github.com/wisent/wisent-visuals
Project-URL: Documentation, https://github.com/wisent/wisent-visuals#readme
Project-URL: Repository, https://github.com/wisent/wisent-visuals
Project-URL: Issues, https://github.com/wisent/wisent-visuals/issues
Keywords: plotting,visualization,charts,branding,matplotlib
Classifier: Development Status :: 3 - Alpha
Classifier: Intended Audience :: Developers
Classifier: Intended Audience :: Science/Research
Classifier: License :: OSI Approved :: MIT License
Classifier: Programming Language :: Python :: 3
Classifier: Programming Language :: Python :: 3.8
Classifier: Programming Language :: Python :: 3.9
Classifier: Programming Language :: Python :: 3.10
Classifier: Programming Language :: Python :: 3.11
Classifier: Programming Language :: Python :: 3.12
Classifier: Topic :: Scientific/Engineering :: Visualization
Requires-Python: >=3.8
License-File: LICENSE
Requires-Dist: matplotlib>=3.5.0
Requires-Dist: numpy>=1.20.0
Provides-Extra: dev
Requires-Dist: pytest>=7.0.0; extra == "dev"
Requires-Dist: black>=22.0.0; extra == "dev"
Requires-Dist: isort>=5.10.0; extra == "dev"
Requires-Dist: mypy>=0.950; extra == "dev"
Dynamic: license-file
